sorting_limo/Bubble_sort.py
sorting_limo/Insertion_sort.py
sorting_limo/Quick_sort.py
sorting_limo/__init__.py
sorting_limo/selection_sort.py
sorting_limo-0.1.dist-info/METADATA
sorting_limo-0.1.dist-info/RECORD
sorting_limo-0.1.dist-info/WHEEL
sorting_limo-0.1.dist-info/top_level.txt
