Metadata-Version: 2.1
Name: sorting-limo
Version: 0.1
Summary: 4 differents ways of sorting_limo lists
Home-page: UNKNOWN
Author: Sebastià L.
Author-email: UNKNOWN
License: Sebastià L
Platform: UNKNOWN
